durkinza/cdk_networkfirewall_l2/__init__.py
durkinza/cdk_networkfirewall_l2/py.typed
durkinza/cdk_networkfirewall_l2/_jsii/__init__.py
durkinza/cdk_networkfirewall_l2/_jsii/cdk-networkfirewall-l2@0.1.1.jsii.tgz
durkinza.cdk_networkfirewall_l2-0.1.1.dist-info/LICENSE
durkinza.cdk_networkfirewall_l2-0.1.1.dist-info/METADATA
durkinza.cdk_networkfirewall_l2-0.1.1.dist-info/WHEEL
durkinza.cdk_networkfirewall_l2-0.1.1.dist-info/top_level.txt
durkinza.cdk_networkfirewall_l2-0.1.1.dist-info/RECORD
