Metadata-Version: 2.1
Name: durkinza.cdk-networkfirewall-l2
Version: 0.1.1
Summary: AWS CDK L2 constructs for the AWS Network Firewall (AWS::NetworkFirewall)
Home-page: https://github.com/durkinza/cdk-networkfirewall-l2#readme
Author: durkinza<8985088+durkinza@users.noreply.github.com>
License: Apache-2.0
Project-URL: Source, https://github.com/durkinza/cdk-networkfirewall-l2.git
Classifier: Intended Audience :: Developers
Classifier: Operating System :: OS Independent
Classifier: Programming Language :: JavaScript
Classifier: Programming Language :: Python :: 3 :: Only
Classifier: Programming Language :: Python :: 3.8
Classifier: Programming Language :: Python :: 3.9
Classifier: Programming Language :: Python :: 3.10
Classifier: Programming Language :: Python :: 3.11
Classifier: Typing :: Typed
Classifier: Development Status :: 4 - Beta
Classifier: License :: OSI Approved
Requires-Python: ~=3.8
License-File: LICENSE
Requires-Dist: aws-cdk-lib<3.0.0,>=2.173.2
Requires-Dist: constructs<11.0.0,>=10.0.5
Requires-Dist: jsii<2.0.0,>=1.106.0
Requires-Dist: publication>=0.0.3
Requires-Dist: typeguard<4.3.0,>=2.13.3
